openplugin/__init__.py
openplugin/cli/__init__.py
openplugin/cli/cli.py
openplugin/install/__init__.py
openplugin/install/list_plugins.py
openplugin/install/local_install.py
openplugin/install/remote_install.py
openplugin/install/uninstall.py
openplugin/install/zip_install.py
openplugin/plugin/__init__.py
openplugin/plugin/base_plugin.py
openplugin/plugin/webapp_plugin.py
openplugin/run/__init__.py
openplugin/run/local_run.py
openplugin/template/__init__.py
openplugin/template/base_template.py
openplugin/template/json_template.py
openplugin/template/utils.py
openplugin/template/yaml_template.py
openplugin/utils/__init__.py
openplugin/utils/app_util.py
openplugin/utils/check.py
openplugin/utils/errors.py
openplugin/utils/local_plugin_utils.py
openplugin/utils/network_utils.py
openplugin/utils/util.py
openplugin_py-0.0.8.dist-info/LICENSE
openplugin_py-0.0.8.dist-info/METADATA
openplugin_py-0.0.8.dist-info/WHEEL
openplugin_py-0.0.8.dist-info/entry_points.txt
openplugin_py-0.0.8.dist-info/top_level.txt
openplugin_py-0.0.8.dist-info/RECORD
